fuzzle/__init__.py
fuzzle/controller.py
fuzzle/defuzz.py
fuzzle/exceptions.py
fuzzle/lvars.py
fuzzle/mfs.py
fuzzle/operators.py
fuzzle/plot_utils.py
fuzzle/rules.py
fuzzle/utils.py
fuzzle-0.0.4.dist-info/DESCRIPTION.rst
fuzzle-0.0.4.dist-info/METADATA
fuzzle-0.0.4.dist-info/RECORD
fuzzle-0.0.4.dist-info/WHEEL
fuzzle-0.0.4.dist-info/metadata.json
fuzzle-0.0.4.dist-info/top_level.txt
