Metadata-Version: 2.0
Name: fuzzle
Version: 0.0.4
Summary: A fuzzy controllers library for python
Home-page: http://github.com/blazaid/fuzzle/
Author: blazaid
Author-email: alberto.da@gmail.com
License: GNU General Public License v3
Platform: any
Classifier: Development Status :: 3 - Alpha
Classifier: Intended Audience :: Science/Research
Classifier: License :: OSI Approved :: GNU General Public License v3 (GPLv3)
Classifier: Natural Language :: English
Classifier: Operating System :: OS Independent
Classifier: Programming Language :: Python :: 3.5
Classifier: Topic :: Software Development :: Libraries :: Python Modules
Classifier: Topic :: Scientific/Engineering :: Artificial Intelligence
